google/cloud/tasks/__init__.py
google/cloud/tasks/gapic_version.py
google/cloud/tasks/py.typed
google/cloud/tasks_v2/__init__.py
google/cloud/tasks_v2/gapic_metadata.json
google/cloud/tasks_v2/gapic_version.py
google/cloud/tasks_v2/py.typed
google/cloud/tasks_v2/services/__init__.py
google/cloud/tasks_v2/services/cloud_tasks/__init__.py
google/cloud/tasks_v2/services/cloud_tasks/async_client.py
google/cloud/tasks_v2/services/cloud_tasks/client.py
google/cloud/tasks_v2/services/cloud_tasks/pagers.py
google/cloud/tasks_v2/services/cloud_tasks/transports/__init__.py
google/cloud/tasks_v2/services/cloud_tasks/transports/base.py
google/cloud/tasks_v2/services/cloud_tasks/transports/grpc.py
google/cloud/tasks_v2/services/cloud_tasks/transports/grpc_asyncio.py
google/cloud/tasks_v2/services/cloud_tasks/transports/rest.py
google/cloud/tasks_v2/services/cloud_tasks/transports/rest_base.py
google/cloud/tasks_v2/types/__init__.py
google/cloud/tasks_v2/types/cloudtasks.py
google/cloud/tasks_v2/types/queue.py
google/cloud/tasks_v2/types/target.py
google/cloud/tasks_v2/types/task.py
google/cloud/tasks_v2beta2/__init__.py
google/cloud/tasks_v2beta2/gapic_metadata.json
google/cloud/tasks_v2beta2/gapic_version.py
google/cloud/tasks_v2beta2/py.typed
google/cloud/tasks_v2beta2/services/__init__.py
google/cloud/tasks_v2beta2/services/cloud_tasks/__init__.py
google/cloud/tasks_v2beta2/services/cloud_tasks/async_client.py
google/cloud/tasks_v2beta2/services/cloud_tasks/client.py
google/cloud/tasks_v2beta2/services/cloud_tasks/pagers.py
google/cloud/tasks_v2beta2/services/cloud_tasks/transports/__init__.py
google/cloud/tasks_v2beta2/services/cloud_tasks/transports/base.py
google/cloud/tasks_v2beta2/services/cloud_tasks/transports/grpc.py
google/cloud/tasks_v2beta2/services/cloud_tasks/transports/grpc_asyncio.py
google/cloud/tasks_v2beta2/services/cloud_tasks/transports/rest.py
google/cloud/tasks_v2beta2/services/cloud_tasks/transports/rest_base.py
google_cloud_tasks-2.19.2.dist-info/LICENSE
google_cloud_tasks-2.19.2.dist-info/METADATA
google_cloud_tasks-2.19.2.dist-info/WHEEL
google_cloud_tasks-2.19.2.dist-info/top_level.txt
google_cloud_tasks-2.19.2.dist-info/RECORD
